kernel/__init__.py
kernel/_base_client.py
kernel/_client.py
kernel/_compat.py
kernel/_constants.py
kernel/_exceptions.py
kernel/_files.py
kernel/_models.py
kernel/_qs.py
kernel/_resource.py
kernel/_response.py
kernel/_streaming.py
kernel/_types.py
kernel/_version.py
kernel/app_framework.py
kernel/pagination.py
kernel/py.typed
kernel/_utils/__init__.py
kernel/_utils/_compat.py
kernel/_utils/_datetime_parse.py
kernel/_utils/_json.py
kernel/_utils/_logs.py
kernel/_utils/_proxy.py
kernel/_utils/_reflection.py
kernel/_utils/_resources_proxy.py
kernel/_utils/_streams.py
kernel/_utils/_sync.py
kernel/_utils/_transform.py
kernel/_utils/_typing.py
kernel/_utils/_utils.py
kernel/lib/.keep
kernel/resources/__init__.py
kernel/resources/apps.py
kernel/resources/browser_pools.py
kernel/resources/credential_providers.py
kernel/resources/credentials.py
kernel/resources/deployments.py
kernel/resources/extensions.py
kernel/resources/invocations.py
kernel/resources/profiles.py
kernel/resources/proxies.py
kernel/resources/agents/__init__.py
kernel/resources/agents/agents.py
kernel/resources/agents/auth/__init__.py
kernel/resources/agents/auth/auth.py
kernel/resources/agents/auth/invocations.py
kernel/resources/browsers/__init__.py
kernel/resources/browsers/browsers.py
kernel/resources/browsers/computer.py
kernel/resources/browsers/logs.py
kernel/resources/browsers/playwright.py
kernel/resources/browsers/process.py
kernel/resources/browsers/replays.py
kernel/resources/browsers/fs/__init__.py
kernel/resources/browsers/fs/fs.py
kernel/resources/browsers/fs/watch.py
kernel/types/__init__.py
kernel/types/app_list_params.py
kernel/types/app_list_response.py
kernel/types/browser_create_params.py
kernel/types/browser_create_response.py
kernel/types/browser_delete_params.py
kernel/types/browser_list_params.py
kernel/types/browser_list_response.py
kernel/types/browser_load_extensions_params.py
kernel/types/browser_persistence.py
kernel/types/browser_persistence_param.py
kernel-0.29.0.dist-info/METADATA
kernel-0.29.0.dist-info/WHEEL
kernel-0.29.0.dist-info/licenses/LICENSE
kernel-0.29.0.dist-info/RECORD
